PyOpenGL_game-1.2.dist-info/RECORD
PyOpenGL_game-1.2.dist-info/WHEEL
PyOpenGL_game-1.2.dist-info/DESCRIPTION.rst
PyOpenGL_game-1.2.dist-info/metadata.json
PyOpenGL_game-1.2.dist-info/top_level.txt
PyOpenGL_game-1.2.dist-info/METADATA
PyOpenGL_game-1.2.dist-info/entry_points.txt
PyOpenGL_game/__init__.py
PyOpenGL_game/shader.py
PyOpenGL_game/event.py
PyOpenGL_game/player.py
PyOpenGL_game/main.py
PyOpenGL_game/Fragment.frag
PyOpenGL_game/glfont.py
PyOpenGL_game/objectquad.py
PyOpenGL_game/engine.py
PyOpenGL_game/bull.py
PyOpenGL_game/game.py
PyOpenGL_game/globject.py
PyOpenGL_game/texture.py
PyOpenGL_game/objectcube.py
PyOpenGL_game/setup.py
PyOpenGL_game/item.py
PyOpenGL_game/shaderprogram.py
PyOpenGL_game/Vertex.vert
PyOpenGL_game/libglfw.so
PyOpenGL_game/gui.py
PyOpenGL_game/event.list
PyOpenGL_game/glutils.py
PyOpenGL_game/glfw.py
PyOpenGL_game/data/e2.png
PyOpenGL_game/data/e3.png
PyOpenGL_game/data/e6.png
PyOpenGL_game/data/item.png
PyOpenGL_game/data/e5.png
PyOpenGL_game/data/e4.png
PyOpenGL_game/data/aim.png
PyOpenGL_game/data/e1.png
PyOpenGL_game/data/mono.ttf
PyOpenGL_game/data/radar.png
PyOpenGL_game/data/e7.png
PyOpenGL_game/localization/text.pot
PyOpenGL_game/localization/text.po
PyOpenGL_game/localization/ru/LC_MESSAGES/text.mo
