Metadata-Version: 2.0
Name: PyOpenGL-game
Version: 1.2
Summary: Simple OpenGL game
Home-page: UNKNOWN
Author: Vladimir Zhukov
Author-email: zhvv117@gmail.com
License: MIT
Platform: UNKNOWN
Classifier: Development Status :: 3 - Alpha
Classifier: Environment :: X11 Applications
Classifier: Operating System :: POSIX :: Linux
Classifier: Programming Language :: Python :: 2.7
Classifier: Topic :: Games/Entertainment
Classifier: License :: OSI Approved :: MIT License
Requires-Dist: numpy
Requires-Dist: pyopengl
Requires-Dist: pypng
Requires-Dist: pillow
